tinyml_compress/__init__.py
tinyml_compress/convert.py
tinyml_compress/distill.py
tinyml_compress/prune.py
tinyml_compress/quant.py
tinyml_compress-1.0.1.dist-info/LICENSE
tinyml_compress-1.0.1.dist-info/METADATA
tinyml_compress-1.0.1.dist-info/WHEEL
tinyml_compress-1.0.1.dist-info/top_level.txt
tinyml_compress-1.0.1.dist-info/RECORD
