Metadata-Version: 2.1
Name: tinyml-compress
Version: 1.0.1
Summary: A library for converting, optimizing, and saving/loading machine learning models.
Home-page: https://github.com/Lawrence-Menegus/tinyml_compress
Author: Lawrence Menegus
Author-email: lmenegus7@gmail.com
Classifier: Programming Language :: Python :: 3
Classifier: License :: OSI Approved :: MIT License
Classifier: Operating System :: OS Independent
Requires-Python: >=3.6
License-File: LICENSE
Requires-Dist: tensorflow >=2.0
Requires-Dist: torch >=1.6
Requires-Dist: tensorflow-model-optimization
